{
    "id": "impmal-rtim",
    "title": "ImpMal - rTIM",
    "version": "0.16.0",
    "manifest": "REPLACED BY BUILD",
    "url": "REPLACED BY BUILD",
    "download": "REPLACED BY BUILD",
    "compatibility": {
        "minimum": "12",
        "verified": "12"
    },
    "relationships": {
        "systems": [
            {
                "id": "impmal",
                "type": "system",
                "compatibility": {}
            }
        ]
    },
  "esmodules": [ "baseBuilding/baseBuilding.js", "settings/settings.js" ],
    "styles": [],
    "languages": [
        {
            "lang": "en",
            "name": "English",
            "path": "languages/en.json",
            "flags": {}
        }
    ],
    "packFolders": [
        {
            "name": "rTIM",
            "sorting": "m",
          "packs": [ "base-modules", "rtim-rolltables", "rtim-cards", "rtim-journalentries", "rtim-macros", "rtim-actors" ]
        }
    ],
  "packs": [
    {
      "name": "base-modules",
      "label": "rTIM-Items",
      "path": "packs/base-modules",
      "type": "Item",
      "system": "impmal",
      "ownership": {
        "PLAYER": "OBSERVER",
        "ASSISTANT": "OWNER"
      }
    },
    {
      "name": "rtim-rolltables",
      "label": "rTIM-RollTables",
      "path": "packs/rtim-rolltables",
      "type": "RollTable",
      "ownership": {
        "PLAYER": "OBSERVER",
        "ASSISTANT": "OWNER"
      },
      "system": "impmal"
    },
    {
      "name": "rtim-cards",
      "label": "rTIM-Cards",
      "path": "packs/rtim-cards",
      "type": "Cards",
      "ownership": {
        "PLAYER": "OBSERVER",
        "ASSISTANT": "OWNER"
      },
      "system": "impmal"
    },
    {
      "name": "rtim-journalentries",
      "label": "rTIM-JournalEntries",
      "path": "packs/rtim-journalentries",
      "type": "JournalEntry",
      "system": "impmal",
      "ownership": {
        "PLAYER": "OBSERVER",
        "ASSISTANT": "OWNER"
      }
    },
    {
      "name": "rtim-macros",
      "label": "rTIM-Macros",
      "path": "packs/rtim-macros",
      "type": "Macro",
      "ownership": {
        "PLAYER": "OBSERVER",
        "ASSISTANT": "OWNER"
      },
      "system": "impmal"
    },
    {
      "name": "rtim-actors",
      "label": "rTIM-Actors",
      "path": "packs/rtim-actors",
      "type": "Actor",
      "ownership": {
        "PLAYER": "OBSERVER",
        "ASSISTANT": "OWNER"
      },
      "system": "impmal"
    }
  ],
    "documentTypes": {
        "Actor": {
            "baseBuilding": {}
        },
        "Item": {
            "module": {}
        }
    }
}

